openapi_client/__init__.py
openapi_client/api_client.py
openapi_client/configuration.py
openapi_client/exceptions.py
openapi_client/model_utils.py
openapi_client/rest.py
openapi_client/api/__init__.py
openapi_client/api/genres_api.py
openapi_client/api/lists_api.py
openapi_client/api/movies_api.py
openapi_client/api/oauth2_api.py
openapi_client/api/users_api.py
openapi_client/apis/__init__.py
openapi_client/model/__init__.py
openapi_client/model/genre.py
openapi_client/model/http_validation_error.py
openapi_client/model/list_create.py
openapi_client/model/list_schema.py
openapi_client/model/list_update.py
openapi_client/model/movie.py
openapi_client/model/token.py
openapi_client/model/user.py
openapi_client/model/user_create.py
openapi_client/model/user_update.py
openapi_client/model/validation_error.py
openapi_client/models/__init__.py
oscar_local_openapi_client-1.0.0.dist-info/METADATA
oscar_local_openapi_client-1.0.0.dist-info/WHEEL
oscar_local_openapi_client-1.0.0.dist-info/top_level.txt
oscar_local_openapi_client-1.0.0.dist-info/RECORD
