Metadata-Version: 2.1
Name: oscar-local-openapi-client
Version: 1.0.0
Summary: FastAPI
Home-page: 
Author: OpenAPI Generator community
Author-email: team@openapitools.org
Keywords: OpenAPI,OpenAPI-Generator,FastAPI
Requires-Python: >=3.6
Requires-Dist: urllib3 (>=1.25.3)
Requires-Dist: python-dateutil
